wake_ai/__init__.py
wake_ai/cli.py
wake_ai/detections.py
wake_ai/results.py
wake_ai/core/__init__.py
wake_ai/core/claude.py
wake_ai/core/exceptions.py
wake_ai/core/flow.py
wake_ai/core/utils.py
wake_ai/flows/__init__.py
wake_ai/flows/audit/__init__.py
wake_ai/flows/audit/result.py
wake_ai/flows/audit/workflow.py
wake_ai/flows/audit/prompts/0-initialize.md
wake_ai/flows/audit/prompts/1-analyze-and-plan.md
wake_ai/flows/audit/prompts/2-manual-review.md
wake_ai/flows/audit/prompts/3-executive-summary.md
wake_ai/flows/donation_attack/__init__.py
wake_ai/flows/donation_attack/workflow.py
wake_ai/flows/reentrancy/__init__.py
wake_ai/flows/reentrancy/workflow.py
wake_ai/flows/uniswap_integration/__init__.py
wake_ai/flows/uniswap_integration/workflow.py
wake_ai/printers/__init__.py
wake_ai/templates/__init__.py
wake_ai/templates/simple_detector.py
wake_ai/utils/__init__.py
wake_ai/utils/common.py
wake_ai/utils/formatters.py
wake_ai/utils/logging.py
wake_ai/utils/workflow.py
wake_ai-0.2.0.dist-info/METADATA
wake_ai-0.2.0.dist-info/WHEEL
wake_ai-0.2.0.dist-info/entry_points.txt
wake_ai-0.2.0.dist-info/licenses/LICENSE
wake_ai-0.2.0.dist-info/RECORD
