Metadata-Version: 2.4
Name: wake-ai
Version: 0.2.0
Summary: AI-powered smart contract security analysis framework
Project-URL: Homepage, https://github.com/wakehacker/wake-ai
Project-URL: Repository, https://github.com/wakehacker/wake-ai
Author: Ackee Blockchain
License: ISC
License-File: LICENSE
Keywords: ai,audit,claude,ethereum,security,smart-contracts,solidity
Classifier: Development Status :: 3 - Alpha
Classifier: Intended Audience :: Developers
Classifier: License :: OSI Approved :: ISC License (ISCL)
Classifier: Programming Language :: Python :: 3
Classifier: Programming Language :: Python :: 3.10
Classifier: Programming Language :: Python :: 3.11
Classifier: Programming Language :: Python :: 3.12
Classifier: Topic :: Security
Classifier: Topic :: Software Development :: Libraries :: Python Modules
Classifier: Topic :: Software Development :: Testing
Requires-Python: >=3.10
Requires-Dist: claude-code-sdk>=0.0.20
Requires-Dist: click>=8.0
Requires-Dist: eth-wake>=4.20.0
Requires-Dist: jinja2>=3.1
Requires-Dist: pydantic>=2.0
Requires-Dist: pyyaml>=6.0
Requires-Dist: rich-click>=1.8.9
Requires-Dist: rich>=13.3.2
Provides-Extra: dev
Requires-Dist: black>=22.0; extra == 'dev'
Requires-Dist: isort>=5.0; extra == 'dev'
Requires-Dist: mypy>=1.0; extra == 'dev'
